slurmipy/__init__.py
slurmipy/core.py
slurmipy-2024.0.4.dist-info/METADATA
slurmipy-2024.0.4.dist-info/WHEEL
slurmipy-2024.0.4.dist-info/RECORD
