Metadata-Version: 2.3
Name: slurmipy
Version: 2024.0.4
Summary: A package to manage Dask clusters on SLURM systems and execute functions with Dask parallelization.
Project-URL: Homepage, https://github.com/nollde/slurmipy
Project-URL: Issues, https://github.com/nollde/slurmipy/issues
Author-email: Dennis Noll <github@nollde.de>
License: MIT License
Keywords: python,slurm
Classifier: Development Status :: 4 - Beta
Classifier: License :: OSI Approved :: MIT License
Classifier: Programming Language :: Python :: 3
Requires-Python: >=3.8
Requires-Dist: dask-jobqueue
Requires-Dist: dask>=2021.6.0
Requires-Dist: distributed>=2021.6.0
